shapkit/__init__.py
shapkit/_nbdev.py
shapkit/inspector.py
shapkit/monte_carlo_shapley.py
shapkit/plots.py
shapkit/sgd_shapley.py
shapkit/shapley_values.py
shapkit-0.0.4.dist-info/.ipynb_checkpoints/PKG-INFO-checkpoint
shapkit-0.0.4.dist-info/.ipynb_checkpoints/not-zip-safe-checkpoint
shapkit-0.0.4.dist-info/.ipynb_checkpoints/requires-checkpoint.txt
shapkit-0.0.4.dist-info/.ipynb_checkpoints/top_level-checkpoint.txt
shapkit-0.0.4.dist-info/LICENSE
shapkit-0.0.4.dist-info/METADATA
shapkit-0.0.4.dist-info/WHEEL
shapkit-0.0.4.dist-info/entry_points.txt
shapkit-0.0.4.dist-info/top_level.txt
shapkit-0.0.4.dist-info/RECORD
