Metadata-Version: 2.1
Name: shapkit
Version: 0.0.4
Summary: Interpret machine learning predictions using agnostic local feature importance based on Shapley Values.
Home-page: https://github.com/ThalesGroup/shapkit/tree/master/
Author: Simon Grah
Author-email: simon.grah.pro@gmail.com
License: MIT License
Keywords: Attribute Importance Shapley Values
Platform: UNKNOWN
Classifier: Development Status :: 6 - Mature
Classifier: Intended Audience :: Developers
Classifier: License :: OSI Approved :: MIT License
Classifier: Natural Language :: English
Classifier: Programming Language :: Python :: 3.6
Classifier: Programming Language :: Python :: 3.7
Classifier: Programming Language :: Python :: 3.8
Requires-Python: >=3.6
Requires-Dist: numpy (>=1.17.2)
Requires-Dist: pandas (>=0.25.3)
Requires-Dist: matplotlib (>=2.2.3)
Requires-Dist: seaborn (>=0.9.0)
Requires-Dist: tqdm (>=4.26.0)
